spatialbound/__init__.py
spatialbound/api_handler.py
spatialbound/auth.py
spatialbound/chat_handler.py
spatialbound/config.py
spatialbound/geocode_functions.py
spatialbound/live_events_handler.py
spatialbound/location_analyser.py
spatialbound/main.py
spatialbound/map_generator.py
spatialbound/poi_handler.py
spatialbound/route_calculator.py
spatialbound/spatialbound.py
spatialbound/status.py
spatialbound/version.py
spatialbound/video_analyser.py
spatialbound/weather_handler.py
spatialbound/__pycache__/__init__.cpython-310.pyc
spatialbound/__pycache__/api_handler.cpython-310.pyc
spatialbound/__pycache__/auth.cpython-310.pyc
spatialbound/__pycache__/chat_handler.cpython-310.pyc
spatialbound/__pycache__/config.cpython-310.pyc
spatialbound/__pycache__/geocode_functions.cpython-310.pyc
spatialbound/__pycache__/live_events_handler.cpython-310.pyc
spatialbound/__pycache__/location_analyser.cpython-310.pyc
spatialbound/__pycache__/map_generator.cpython-310.pyc
spatialbound/__pycache__/poi_handler.cpython-310.pyc
spatialbound/__pycache__/route_calculator.cpython-310.pyc
spatialbound/__pycache__/spatialbound.cpython-310.pyc
spatialbound/__pycache__/status.cpython-310.pyc
spatialbound/__pycache__/telemetry.cpython-310.pyc
spatialbound/__pycache__/urbani.cpython-310.pyc
spatialbound/__pycache__/version.cpython-310.pyc
spatialbound/__pycache__/video_analyser.cpython-310.pyc
spatialbound/__pycache__/weather_handler.cpython-310.pyc
spatialbound-0.0.8.dist-info/licenses/LICENSE.txt
spatialbound-0.0.8.dist-info/METADATA
spatialbound-0.0.8.dist-info/WHEEL
spatialbound-0.0.8.dist-info/top_level.txt
spatialbound-0.0.8.dist-info/RECORD
