Metadata-Version: 2.4
Name: spatialbound
Version: 0.0.8
Summary: Spatialbound API client library
Home-page: https://github.com/spatialbound/spatialbound_api
Author: Mohamed R. Ibrahim
Author-email: contact@spatialbound.com
Project-URL: Bug Tracker, https://github.com/spatialbound/spatialbound_api/issues
Classifier: Development Status :: 4 - Beta
Classifier: Intended Audience :: Developers
Classifier: Programming Language :: Python :: 3
Classifier: License :: Other/Proprietary License
Classifier: Operating System :: OS Independent
Requires-Python: >=3.6
License-File: LICENSE.txt
Requires-Dist: requests>=2.25.0
Requires-Dist: python-dotenv>=0.15.0
Dynamic: author
Dynamic: author-email
Dynamic: classifier
Dynamic: description
Dynamic: description-content-type
Dynamic: home-page
Dynamic: license-file
Dynamic: project-url
Dynamic: requires-dist
Dynamic: requires-python
Dynamic: summary
